{
 "AssignmentId": "3TOK3KHVJU6ZU6IG020TBHXYDPE7OM",
 "WorkerId": "90b00e0895f30b64de17f7297f370dbf",
 "HITId": "3A9LA2FRWS2GUK4RO04ZXNHX5H6XH0",
 "AssignmentStatus": "Submitted",
 "AutoApprovalTime": "2019-10-18T14:46:06.000Z",
 "AcceptTime": "2019-10-17T14:41:44.000Z",
 "SubmitTime": "2019-10-17T14:46:06.000Z",
 "answers": {
  "trials": [
   {
    "type": "response",
    "plural": "Feps",
    "singular": "Fep",
    "image": "animaltarget.png",
    "featurePlural": "have white wings",
    "featureSingular": "has white wings",
    "distractors": [
     "animaldistractor1.png",
     "animaldistractor2.png",
     "animaldistractor3.png"
    ],
    "response": 0.45,
    "condition": "3accidental"
   },
   {
    "type": "response",
    "plural": "Daxes",
    "singular": "Dax",
    "image": "planttarget.png",
    "featurePlural": "have black centers",
    "featureSingular": "has a black center",
    "distractors": [
     "plantdistractor1.png",
     "plantdistractor2.png",
     "plantdistractor3.png"
    ],
    "response": 0.69,
    "condition": "3accidental"
   },
   {
    "type": "response",
    "distractors": [
     {
      "plural": "Daxes",
      "singular": "Dax",
      "color": "#ff0",
      "greyed": "#999937",
      "sound": "beep",
      "shape": "cylinder",
      "investigator": "Beth",
      "pronoun": "She"
     },
     {
      "plural": "Griffs",
      "singular": "Griff",
      "color": "#8b36c1",
      "greyed": "#602784",
      "sound": "whistle",
      "shape": "hexagon",
      "investigator": "James",
      "pronoun": "He"
     },
     {
      "plural": "Feps",
      "singular": "Fep",
      "color": "#f45042",
      "greyed": "#c14136",
      "sound": "ring",
      "shape": "pyramid",
      "investigator": "Julie",
      "pronoun": "She"
     }
    ],
    "featureSingular": "squeaks",
    "plural": "Blickets",
    "singular": "Blicket",
    "color": "#f44248",
    "greyed": "#992a34",
    "sound": "squeak",
    "shape": "diamond",
    "investigator": "Ashley",
    "pronoun": "She",
    "response": 0.57,
    "condition": "3accidental"
   },
   {
    "type": "id",
    "plural": "Feps",
    "singular": "Fep",
    "image": "animaltarget.png",
    "featurePlural": "have white wings",
    "featureSingular": "has white wings",
    "distractors": [
     "animaldistractor1.png",
     "animaldistractor2.png",
     "animaldistractor3.png"
    ],
    "distractorClicks": 1,
    "selected": "correct",
    "correctId": true,
    "condition": "3accidental"
   },
   {
    "type": "id",
    "plural": "Daxes",
    "singular": "Dax",
    "image": "planttarget.png",
    "featurePlural": "have black centers",
    "featureSingular": "has a black center",
    "distractors": [
     "plantdistractor1.png",
     "plantdistractor2.png",
     "plantdistractor3.png"
    ],
    "distractorClicks": 0,
    "selected": "correct",
    "correctId": true,
    "condition": "3accidental"
   },
   {
    "type": "id",
    "distractors": [
     {
      "plural": "Daxes",
      "singular": "Dax",
      "color": "#ff0",
      "greyed": "#999937",
      "sound": "beep",
      "shape": "cylinder",
      "investigator": "Beth",
      "pronoun": "She"
     },
     {
      "plural": "Griffs",
      "singular": "Griff",
      "color": "#8b36c1",
      "greyed": "#602784",
      "sound": "whistle",
      "shape": "hexagon",
      "investigator": "James",
      "pronoun": "He"
     },
     {
      "plural": "Feps",
      "singular": "Fep",
      "color": "#f45042",
      "greyed": "#c14136",
      "sound": "ring",
      "shape": "pyramid",
      "investigator": "Julie",
      "pronoun": "She"
     }
    ],
    "featureSingular": "squeaks",
    "plural": "Blickets",
    "singular": "Blicket",
    "color": "#f44248",
    "greyed": "#992a34",
    "sound": "squeak",
    "shape": "diamond",
    "investigator": "Ashley",
    "pronoun": "She",
    "distractorClicks": 1,
    "selected": "correct",
    "correctId": true,
    "condition": "3accidental"
   }
  ],
  "system": {
   "Browser": "Chrome",
   "OS": "Windows",
   "screenH": 768,
   "screenW": 1364
  },
  "condition": "3accidental",
  "subject_information": {
   "language": "english",
   "enjoyment": "1",
   "asses": "Yes",
   "age": "24",
   "gender": "Male",
   "education": "3",
   "comments": "nice",
   "problems": "no",
   "fairprice": "no"
  },
  "time_in_minutes": 4.098066666666667,
  "sound_check": {
   "response": "skyscraper",
   "test_word": "evergreen"
  }
 }
}