{
 "AssignmentId": "3QRYMNZ7FZ54AJFBCQ3H1OPCUEHNT4",
 "WorkerId": "d82294e4ff12bcf166e902d4298db9b3",
 "HITId": "3YGE63DIN8LQUKT5GN1SPC4AEYK0W0",
 "AssignmentStatus": "Submitted",
 "AutoApprovalTime": "2020-01-11T04:05:11.000Z",
 "AcceptTime": "2020-01-10T03:09:50.000Z",
 "SubmitTime": "2020-01-10T04:05:11.000Z",
 "answers": {
  "trials": [
   {
    "type": "response",
    "plural": "Feps",
    "singular": "Fep",
    "images": [
     "animaltarget0.png",
     "animaltarget0.png",
     "animaltarget0.png",
     "animaltarget0.png"
    ],
    "featurePlural": "have white wings",
    "featureSingular": "has white wings",
    "distractors": [
     "animaldistractor1.png",
     "animaldistractor2.png",
     "animaldistractor3.png"
    ],
    "sound": "whistle",
    "response": 0.8,
    "condition": "3pedagogical",
    "level": "basic"
   },
   {
    "type": "id",
    "plural": "Feps",
    "singular": "Fep",
    "images": [
     "animaltarget0.png",
     "animaltarget0.png",
     "animaltarget0.png",
     "animaltarget0.png"
    ],
    "featurePlural": "have white wings",
    "featureSingular": "has white wings",
    "distractors": [
     "animaldistractor1.png",
     "animaldistractor2.png",
     "animaldistractor3.png"
    ],
    "sound": "whistle",
    "distractorClicks": 0,
    "selected": "correct",
    "correctId": true,
    "condition": "3pedagogical",
    "level": "basic"
   }
  ],
  "system": {
   "Browser": "Chrome",
   "OS": "Windows",
   "screenH": 768,
   "screenW": 1366
  },
  "condition": "3pedagogical",
  "subject_information": {
   "language": "English",
   "enjoyment": "2",
   "asses": "Yes",
   "age": "53",
   "gender": "Male",
   "education": "4",
   "comments": "Thanks for the opportunity to participate and good luck with your research!",
   "problems": "There were NO problems or bugs with the experiment",
   "fairprice": "0.75"
  },
  "time_in_minutes": 2.653383333333333,
  "sound_check": {
   "response": "evergreen",
   "test_word": "evergreen"
  }
 }
}